{
    "allowed_hwids": [
        {
            "reseller": "rana",
            "username": "ff",
            "displayUsername": "ff",
            "hwid": "fsdfsdfsfsdfsdf",
            "expiryDate": "9999-09-09"
        },
        {
            "reseller": "rana",
            "username": "rr",
            "displayUsername": "rana",
            "hwid": "5eb0d70d-ffc2-45c8-8b88-bf5d66836405",
            "expiryDate": "9999-09-09"
        },
        {
            "reseller": "p2",
            "username": "pranto",
            "hwid": "af8a04f3-13ee-4663-a579-6d8621d486c9",
            "expiryDate": "9999-09-09"
        },
        {
            "reseller": "p2",
            "username": "tanzim",
            "hwid": "449b261a-4a86-4fa8-abd0-615d6f285651",
            "expiryDate": "2028-03-04"
        },
        {
            "reseller": "p2",
            "username": "rohan",
            "hwid": "3a13d59d-0635-42ef-85be-a6f84a8bd7c6",
            "expiryDate": "2029-02-05"
        },
        {
            "reseller": "p2",
            "username": "sadik2",
            "hwid": "1b319037-d0a2-4743-a3f0-ad9463a007c7",
            "expiryDate": "2029-02-08"
        },
        {
            "reseller": "p2",
            "username": "ashik",
            "hwid": "903cc601-a5f8-4d74-be72-a429a68ece14",
            "expiryDate": "2029-04-07"
        },
        {
            "reseller": "p2",
            "username": "eysin",
            "hwid": "5188d066-8664-4307-809f-fab1e29788b2",
            "expiryDate": "2029-02-06"
        },
        {
            "reseller": "p2",
            "username": "faim",
            "hwid": "0e955498-26db-4871-8f43-fb5c52dea06c",
            "expiryDate": "2028-02-08"
        },
        {
            "reseller": "p2",
            "username": "raihim",
            "hwid": "3be37147-045a-46af-a1ef-258b9979c1e1",
            "expiryDate": "2028-03-03"
        }
    ]
}